LICENSE
README.md
pyproject.toml
setup.cfg
setup.py
src/twinstop/__init__.py
src/twinstop/_version.py
src/twinstop/block_selection.py
src/twinstop/denovo_selenoproteins_h3.py
src/twinstop/test_alignment_methods.py
src/twinstop.egg-info/PKG-INFO
src/twinstop.egg-info/SOURCES.txt
src/twinstop.egg-info/dependency_links.txt
src/twinstop.egg-info/requires.txt
src/twinstop.egg-info/top_level.txt
src/twinstop/data_files/Matrix_BLOSUM62sel.txt
src/twinstop/data_files/lr_selenoproteins.1.pkl
src/twinstop/data_files/lr_selenoproteins.10.pkl
src/twinstop/data_files/lr_selenoproteins.100.pkl
src/twinstop/data_files/lr_selenoproteins.1000.pkl
src/twinstop/data_files/lr_selenoproteins.128.pkl
src/twinstop/data_files/lr_selenoproteins.2.pkl
src/twinstop/data_files/lr_selenoproteins.25.pkl
src/twinstop/data_files/lr_selenoproteins.250.pkl
src/twinstop/data_files/lr_selenoproteins.3.pkl
src/twinstop/data_files/lr_selenoproteins.50.pkl
src/twinstop/data_files/lr_selenoproteins.500.pkl
src/twinstop/data_files/lr_selenoproteins.7.pkl
src/twinstop/data_files/lr_selenoproteins.75.pkl
src/twinstop/data_files/lr_selenoproteins.750.pkl
src/twinstop/data_files/scaler.pkl