Metadata-Version: 2.1
Name: twinstop
Version: 0.2.2
Summary: twinstop identifies selenoproteins in close related transcriptomes
Home-page: https://github.com/marco-mariotti/twinstop
Author: Marco Mariotti and Sergio Sanchez Moragues
Author-email: marco.mariotti@ub.edu
Classifier: Programming Language :: Python :: 3
Classifier: License :: OSI Approved :: MIT License
Classifier: Operating System :: OS Independent
Requires-Python: >=3.12
License-File: LICENSE
Requires-Dist: biopython>=1.78
Requires-Dist: easybioinfo>=0.3.1
Requires-Dist: easyterm>=1.0.0
Requires-Dist: file-chunk-iterators>=0.0.1
Requires-Dist: pyranges1>=1.0.0
Requires-Dist: pandas>=2.0.0
Requires-Dist: pyfaidx>=0.7.2
Requires-Dist: multiprocess>=0.70.14
Requires-Dist: numpy>=2.0.0
Requires-Dist: scikit-learn>=1.3.0
